CyberHerder/DateRanger.py
CyberHerder/GenerateCompanies.py
CyberHerder/GenerateCreditCard.py
CyberHerder/GenerateCreditCards.py
CyberHerder/GenerateDataBreach.py
CyberHerder/GenerateEmails.py
CyberHerder/GenerateGPS.py
CyberHerder/GenerateIPv4Addresses.py
CyberHerder/GenerateIPv6Addresses.py
CyberHerder/GenerateMACAddresses.py
CyberHerder/GeneratePasswords.py
CyberHerder/GeneratePhoneNumbers.py
CyberHerder/GeneratePins.py
CyberHerder/GeneratePostalCodes.py
CyberHerder/GenerateUids.py
CyberHerder/GenerateUsernames.py
CyberHerder/__init__.py
CyberHerder/generator.py
CyberHerder/verification.py
CyberHerder-2.0.0.dist-info/LICENSE
CyberHerder-2.0.0.dist-info/METADATA
CyberHerder-2.0.0.dist-info/WHEEL
CyberHerder-2.0.0.dist-info/top_level.txt
CyberHerder-2.0.0.dist-info/RECORD
