Metadata-Version: 2.1
Name: CyberHerder
Version: 2.0.0
Home-page: 
Author: jacob.h.barrow
Author-email: jacob.h.barrow@gmail.com
License: MIT
Classifier: License :: OSI Approved :: MIT License
Classifier: Programming Language :: Python
Classifier: Programming Language :: Python :: 3
License-File: LICENSE
Requires-Dist: scipy
Requires-Dist: numpy
Requires-Dist: pandas
